tp/__init__.py
tp/test/__init__.py
tp/test/fixtures/__init__.py
tp/test/fixtures/common.py
tp_py_common-2.0.4.dist-info/METADATA
tp_py_common-2.0.4.dist-info/WHEEL
tp_py_common-2.0.4.dist-info/top_level.txt
tp_py_common-2.0.4.dist-info/RECORD
