Metadata-Version: 2.1
Name: tp-py-common
Version: 2.0.4
Summary: Common code to be used by various tp packages
Home-page: UNKNOWN
Author: TruePill
Author-email: UNKNOWN
License: UNKNOWN
Platform: UNKNOWN
